causal_experiment/__init__.py
causal_experiment/dataset.py
causal_experiment/train_small_causal_model.py
causal_experiment/components/calculator_components.py
causal_experiment/eval/model_eval.py
causal_experiment/modules/calculator_view.py
causal_experiment-0.2.3.dist-info/METADATA
causal_experiment-0.2.3.dist-info/WHEEL
causal_experiment-0.2.3.dist-info/entry_points.txt
causal_experiment-0.2.3.dist-info/licenses/LICENSE
causal_experiment-0.2.3.dist-info/RECORD
